[
  {
    "MapId": 1,
    "MapName": "Country_1_Title",
    "FatherMap": 0,
    "GroupMark": 0,
    "Floor": 0,
    "SwitchCondition": "",
    "MapPic3d": "PL_AkiWorld001",
    "MapPic2d": "",
    "BigMapDefaultScale": 200,
    "BigMapMinScale": 150,
    "BigMapMaxScale": 500,
    "LittleMapDefaultScale": 1000,
    "LimitContent": "limit()",
    "IsGravityMap": false
  },
  {
    "MapId": 2,
    "MapName": "Country_1_Title",
    "FatherMap": 1,
    "GroupMark": 2000,
    "Floor": -1,
    "SwitchCondition": "",
    "MapPic3d": "",
    "MapPic2d": "",
    "BigMapDefaultScale": 100,
    "BigMapMinScale": 0,
    "BigMapMaxScale": 0,
    "LittleMapDefaultScale": 100,
    "LimitContent": "limit()",
    "IsGravityMap": false
  },
  {
    "MapId": 3,
    "MapName": "Country_1_Title",
    "FatherMap": 1,
    "GroupMark": 2000,
    "Floor": 1,
    "SwitchCondition": "",
    "MapPic3d": "",
    "MapPic2d": "",
    "BigMapDefaultScale": 100,
    "BigMapMinScale": 0,
    "BigMapMaxScale": 0,
    "LittleMapDefaultScale": 100,
    "LimitContent": "limit()",
    "IsGravityMap": false
  },
  {
    "MapId": 4,
    "MapName": "Country_1_Title",
    "FatherMap": 1,
    "GroupMark": 2000,
    "Floor": 2,
    "SwitchCondition": "",
    "MapPic3d": "",
    "MapPic2d": "",
    "BigMapDefaultScale": 100,
    "BigMapMinScale": 0,
    "BigMapMaxScale": 0,
    "LittleMapDefaultScale": 100,
    "LimitContent": "limit()",
    "IsGravityMap": false
  },
  {
    "MapId": 5,
    "MapName": "Country_1_Title",
    "FatherMap": 1,
    "GroupMark": 2000,
    "Floor": 3,
    "SwitchCondition": "",
    "MapPic3d": "",
    "MapPic2d": "",
    "BigMapDefaultScale": 100,
    "BigMapMinScale": 0,
    "BigMapMaxScale": 0,
    "LittleMapDefaultScale": 100,
    "LimitContent": "limit()",
    "IsGravityMap": false
  },
  {
    "MapId": 6,
    "MapName": "Country_1_Title",
    "FatherMap": 1,
    "GroupMark": 2001,
    "Floor": -3,
    "SwitchCondition": "",
    "MapPic3d": "",
    "MapPic2d": "",
    "BigMapDefaultScale": 100,
    "BigMapMinScale": 0,
    "BigMapMaxScale": 0,
    "LittleMapDefaultScale": 100,
    "LimitContent": "limit()",
    "IsGravityMap": false
  },
  {
    "MapId": 7,
    "MapName": "Country_1_Title",
    "FatherMap": 1,
    "GroupMark": 2001,
    "Floor": -2,
    "SwitchCondition": "",
    "MapPic3d": "",
    "MapPic2d": "",
    "BigMapDefaultScale": 100,
    "BigMapMinScale": 0,
    "BigMapMaxScale": 0,
    "LittleMapDefaultScale": 100,
    "LimitContent": "limit()",
    "IsGravityMap": false
  },
  {
    "MapId": 8,
    "MapName": "Country_1_Title",
    "FatherMap": 1,
    "GroupMark": 2001,
    "Floor": -1,
    "SwitchCondition": "",
    "MapPic3d": "",
    "MapPic2d": "",
    "BigMapDefaultScale": 200,
    "BigMapMinScale": 180,
    "BigMapMaxScale": 700,
    "LittleMapDefaultScale": 150,
    "LimitContent": "limit()",
    "IsGravityMap": false
  },
  {
    "MapId": 9,
    "MapName": "Country_1_Title",
    "FatherMap": 1,
    "GroupMark": 2001,
    "Floor": 1,
    "SwitchCondition": "",
    "MapPic3d": "",
    "MapPic2d": "",
    "BigMapDefaultScale": 100,
    "BigMapMinScale": 0,
    "BigMapMaxScale": 0,
    "LittleMapDefaultScale": 100,
    "LimitContent": "limit()",
    "IsGravityMap": false
  },
  {
    "MapId": 900,
    "MapName": "Country_2_Title",
    "FatherMap": 1,
    "GroupMark": 2001,
    "Floor": -1,
    "SwitchCondition": "",
    "MapPic3d": "",
    "MapPic2d": "",
    "BigMapDefaultScale": 200,
    "BigMapMinScale": 180,
    "BigMapMaxScale": 700,
    "LittleMapDefaultScale": 150,
    "LimitContent": "limit()",
    "IsGravityMap": false
  },
  {
    "MapId": 903,
    "MapName": "Area_25_Title",
    "FatherMap": 1,
    "GroupMark": 2001,
    "Floor": -1,
    "SwitchCondition": "",
    "MapPic3d": "",
    "MapPic2d": "",
    "BigMapDefaultScale": 200,
    "BigMapMinScale": 180,
    "BigMapMaxScale": 700,
    "LittleMapDefaultScale": 150,
    "LimitContent": "limit()",
    "IsGravityMap": true
  },
  {
    "MapId": 902,
    "MapName": "Area_27_Title",
    "FatherMap": 1,
    "GroupMark": 2001,
    "Floor": -1,
    "SwitchCondition": "",
    "MapPic3d": "",
    "MapPic2d": "",
    "BigMapDefaultScale": 200,
    "BigMapMinScale": 180,
    "BigMapMaxScale": 700,
    "LittleMapDefaultScale": 150,
    "LimitContent": "limit()",
    "IsGravityMap": false
  },
  {
    "MapId": 9301,
    "MapName": "团子小世界",
    "FatherMap": 1,
    "GroupMark": 2001,
    "Floor": -1,
    "SwitchCondition": "",
    "MapPic3d": "",
    "MapPic2d": "",
    "BigMapDefaultScale": 200,
    "BigMapMinScale": 180,
    "BigMapMaxScale": 700,
    "LittleMapDefaultScale": 150,
    "LimitContent": "limit()",
    "IsGravityMap": false
  }
]