[
  {
    "Id": 207850048,
    "InstId": 8760,
    "EntityConfigId": 207850048
  },
  {
    "Id": 207850031,
    "InstId": 8760,
    "EntityConfigId": 207850031
  },
  {
    "Id": 207850146,
    "InstId": 8760,
    "EntityConfigId": 207850146
  },
  {
    "Id": 207850049,
    "InstId": 8760,
    "EntityConfigId": 207850049
  },
  {
    "Id": 207850050,
    "InstId": 8760,
    "EntityConfigId": 207850050
  },
  {
    "Id": 207850051,
    "InstId": 8760,
    "EntityConfigId": 207850051
  },
  {
    "Id": 207850054,
    "InstId": 8760,
    "EntityConfigId": 207850054
  }
]