[
  {
    "Id": 1001,
    "RoleId": 1402,
    "FormulaId": 10016,
    "CookProbability": 20,
    "ItemId": 80001016,
    "AttributesDescription": ""
  },
  {
    "Id": 1002,
    "RoleId": 1202,
    "FormulaId": 10025,
    "CookProbability": 20,
    "ItemId": 80001025,
    "AttributesDescription": ""
  },
  {
    "Id": 1003,
    "RoleId": 1103,
    "FormulaId": 10002,
    "CookProbability": 20,
    "ItemId": 80001002,
    "AttributesDescription": ""
  },
  {
    "Id": 1004,
    "RoleId": 1102,
    "FormulaId": 10012,
    "CookProbability": 20,
    "ItemId": 80001012,
    "AttributesDescription": ""
  },
  {
    "Id": 1005,
    "RoleId": 1204,
    "FormulaId": 10024,
    "CookProbability": 20,
    "ItemId": 80001024,
    "AttributesDescription": ""
  },
  {
    "Id": 1006,
    "RoleId": 1602,
    "FormulaId": 10004,
    "CookProbability": 20,
    "ItemId": 80001004,
    "AttributesDescription": ""
  },
  {
    "Id": 1007,
    "RoleId": 1601,
    "FormulaId": 10020,
    "CookProbability": 20,
    "ItemId": 80001020,
    "AttributesDescription": ""
  },
  {
    "Id": 1008,
    "RoleId": 1404,
    "FormulaId": 10014,
    "CookProbability": 20,
    "ItemId": 80001014,
    "AttributesDescription": ""
  },
  {
    "Id": 1009,
    "RoleId": 1302,
    "FormulaId": 10017,
    "CookProbability": 20,
    "ItemId": 80001017,
    "AttributesDescription": ""
  },
  {
    "Id": 1010,
    "RoleId": 1301,
    "FormulaId": 10005,
    "CookProbability": 20,
    "ItemId": 80001005,
    "AttributesDescription": ""
  },
  {
    "Id": 1011,
    "RoleId": 1303,
    "FormulaId": 10008,
    "CookProbability": 20,
    "ItemId": 80001008,
    "AttributesDescription": ""
  },
  {
    "Id": 1012,
    "RoleId": 1104,
    "FormulaId": 10000,
    "CookProbability": 20,
    "ItemId": 80001000,
    "AttributesDescription": ""
  },
  {
    "Id": 1013,
    "RoleId": 1405,
    "FormulaId": 10023,
    "CookProbability": 20,
    "ItemId": 80001023,
    "AttributesDescription": ""
  },
  {
    "Id": 1014,
    "RoleId": 1503,
    "FormulaId": 10029,
    "CookProbability": 20,
    "ItemId": 80001029,
    "AttributesDescription": ""
  },
  {
    "Id": 1015,
    "RoleId": 1203,
    "FormulaId": 10021,
    "CookProbability": 20,
    "ItemId": 80001021,
    "AttributesDescription": ""
  },
  {
    "Id": 1016,
    "RoleId": 1403,
    "FormulaId": 10032,
    "CookProbability": 20,
    "ItemId": 80001032,
    "AttributesDescription": ""
  },
  {
    "Id": 1017,
    "RoleId": 1304,
    "FormulaId": 10033,
    "CookProbability": 20,
    "ItemId": 80001033,
    "AttributesDescription": ""
  },
  {
    "Id": 1018,
    "RoleId": 1205,
    "FormulaId": 10034,
    "CookProbability": 20,
    "ItemId": 80001034,
    "AttributesDescription": ""
  },
  {
    "Id": 1019,
    "RoleId": 1305,
    "FormulaId": 10035,
    "CookProbability": 20,
    "ItemId": 80001035,
    "AttributesDescription": ""
  },
  {
    "Id": 1020,
    "RoleId": 1105,
    "FormulaId": 10001,
    "CookProbability": 20,
    "ItemId": 80001001,
    "AttributesDescription": ""
  },
  {
    "Id": 1021,
    "RoleId": 1505,
    "FormulaId": 10039,
    "CookProbability": 20,
    "ItemId": 80001039,
    "AttributesDescription": ""
  },
  {
    "Id": 1022,
    "RoleId": 1106,
    "FormulaId": 10040,
    "CookProbability": 20,
    "ItemId": 80001040,
    "AttributesDescription": ""
  },
  {
    "Id": 1023,
    "RoleId": 1603,
    "FormulaId": 10007,
    "CookProbability": 20,
    "ItemId": 80001007,
    "AttributesDescription": ""
  },
  {
    "Id": 1024,
    "RoleId": 1504,
    "FormulaId": 10011,
    "CookProbability": 20,
    "ItemId": 80001011,
    "AttributesDescription": ""
  },
  {
    "Id": 1025,
    "RoleId": 1107,
    "FormulaId": 10045,
    "CookProbability": 20,
    "ItemId": 80001045,
    "AttributesDescription": ""
  },
  {
    "Id": 1026,
    "RoleId": 1606,
    "FormulaId": 10043,
    "CookProbability": 20,
    "ItemId": 80001043,
    "AttributesDescription": ""
  },
  {
    "Id": 1027,
    "RoleId": 1506,
    "FormulaId": 10041,
    "CookProbability": 20,
    "ItemId": 80001041,
    "AttributesDescription": ""
  },
  {
    "Id": 1028,
    "RoleId": 1206,
    "FormulaId": 10052,
    "CookProbability": 20,
    "ItemId": 80001052,
    "AttributesDescription": ""
  },
  {
    "Id": 1029,
    "RoleId": 1607,
    "FormulaId": 10049,
    "CookProbability": 20,
    "ItemId": 80001049,
    "AttributesDescription": ""
  },
  {
    "Id": 1030,
    "RoleId": 1407,
    "FormulaId": 10051,
    "CookProbability": 20,
    "ItemId": 80001051,
    "AttributesDescription": ""
  },
  {
    "Id": 1031,
    "RoleId": 1507,
    "FormulaId": 10044,
    "CookProbability": 20,
    "ItemId": 80001044,
    "AttributesDescription": ""
  },
  {
    "Id": 1032,
    "RoleId": 1207,
    "FormulaId": 10061,
    "CookProbability": 20,
    "ItemId": 80001061,
    "AttributesDescription": ""
  },
  {
    "Id": 1033,
    "RoleId": 1409,
    "FormulaId": 10047,
    "CookProbability": 20,
    "ItemId": 80001047,
    "AttributesDescription": ""
  },
  {
    "Id": 1034,
    "RoleId": 1608,
    "FormulaId": 10057,
    "CookProbability": 20,
    "ItemId": 80001057,
    "AttributesDescription": ""
  },
  {
    "Id": 1035,
    "RoleId": 1410,
    "FormulaId": 10065,
    "CookProbability": 20,
    "ItemId": 80001065,
    "AttributesDescription": ""
  },
  {
    "Id": 1036,
    "RoleId": 1306,
    "FormulaId": 10066,
    "CookProbability": 20,
    "ItemId": 80001066,
    "AttributesDescription": ""
  },
  {
    "Id": 1037,
    "RoleId": 1208,
    "FormulaId": 10060,
    "CookProbability": 20,
    "ItemId": 80001060,
    "AttributesDescription": ""
  },
  {
    "Id": 1038,
    "RoleId": 1411,
    "FormulaId": 10028,
    "CookProbability": 20,
    "ItemId": 80001028,
    "AttributesDescription": ""
  },
  {
    "Id": 1039,
    "RoleId": 1508,
    "FormulaId": 10018,
    "CookProbability": 20,
    "ItemId": 80001018,
    "AttributesDescription": ""
  },
  {
    "Id": 1040,
    "RoleId": 1307,
    "FormulaId": 10019,
    "CookProbability": 20,
    "ItemId": 80001019,
    "AttributesDescription": ""
  },
  {
    "Id": 1041,
    "RoleId": 1509,
    "FormulaId": 10081,
    "CookProbability": 20,
    "ItemId": 80001081,
    "AttributesDescription": ""
  },
  {
    "Id": 1042,
    "RoleId": 1209,
    "FormulaId": 10079,
    "CookProbability": 20,
    "ItemId": 80001079,
    "AttributesDescription": ""
  }
]